deepapi/__init__.py
deepapi/__main__.py
deepapi/_main.py
deepapi/api/__init__.py
deepapi/dataset/__init__.py
deepapi/dataset/cifar10.py
deepapi/dataset/imagenet.py
deepapi/dataset/imagenet_class_index.py
deepapi/models/__init__.py
deepapi/models/inceptionv3.py
deepapi/models/resnet50.py
deepapi/models/vgg16.py
deepapi/static/font.js
deepapi/static/index.html
deepapi/static/script.js
deepapi/static/simpleSnackbar.min.css
deepapi/static/simpleSnackbar.min.js
deepapi/static/style.css
deepapi/static/upload.js
deepapi/utils/__init__.py
deepapi/utils/response.py
deepapi-0.4.3.data/data/_lib/runtime/font.js
deepapi-0.4.3.data/data/_lib/runtime/index.html
deepapi-0.4.3.data/data/_lib/runtime/script.js
deepapi-0.4.3.data/data/_lib/runtime/simpleSnackbar.min.css
deepapi-0.4.3.data/data/_lib/runtime/simpleSnackbar.min.js
deepapi-0.4.3.data/data/_lib/runtime/style.css
deepapi-0.4.3.data/data/_lib/runtime/upload.js
deepapi-0.4.3.dist-info/LICENSE
deepapi-0.4.3.dist-info/METADATA
deepapi-0.4.3.dist-info/WHEEL
deepapi-0.4.3.dist-info/entry_points.txt
deepapi-0.4.3.dist-info/top_level.txt
deepapi-0.4.3.dist-info/RECORD
