Metadata-Version: 2.1
Name: deepapi
Version: 0.4.3
Summary: Deep Learning as a Cloud API Service.
Home-page: https://github.com/wuhanstudio/deepapi
Author: wuhanstudio
Author-email: wuhanstudio <wuhanstudios@gmail.com>
Maintainer: wuhanstudio
Maintainer-email: wuhanstudio <wuhanstudios@gmail.com>
License: MIT License
Project-URL: Homepage, https://github.com/wuhanstudio/deepapi
Project-URL: Bug Tracker, https://github.com/wuhanstudio/deepapi/issues
Classifier: Programming Language :: Python :: 3
Classifier: License :: OSI Approved :: MIT License
Classifier: Operating System :: OS Independent
Requires-Python: >=3.6
License-File: LICENSE
Requires-Dist: setuptools (>=61.0)
Requires-Dist: flask
Requires-Dist: waitress
Requires-Dist: grpcio
Requires-Dist: h5py
Requires-Dist: keras
Requires-Dist: keras-preprocessing
Requires-Dist: numpy
Requires-Dist: pillow
Requires-Dist: requests
Requires-Dist: tensorflow
